core.py
ibolang.py
ig_tran.py
igbolang.py
ibolang-0.0.2.dist-info/METADATA
ibolang-0.0.2.dist-info/WHEEL
ibolang-0.0.2.dist-info/entry_points.txt
ibolang-0.0.2.dist-info/top_level.txt
ibolang-0.0.2.dist-info/RECORD
