Metadata-Version: 2.1
Name: ibolang
Version: 0.0.2
Summary: programming language in Igbo
Home-page: https://github.com/ORC-1/ibolang
Author: Roland|Chima
Author-email: Rolandazim@gmail.com
License: See https://www.python.org/psf/license/
Download-URL: https://github.com/ORC-1/ibolang
Keywords: traditional,simplified,Igbo,Afrocode,language,tokenize
Platform: UNKNOWN
Classifier: Development Status :: 4 - Beta
Classifier: Environment :: Console
Classifier: Intended Audience :: Education
Classifier: Intended Audience :: Developers
Classifier: Intended Audience :: System Administrators
Classifier: License :: OSI Approved :: MIT License
Classifier: Operating System :: OS Independent
Classifier: Programming Language :: Python
Classifier: Topic :: Software Development :: Libraries :: Python Modules
Classifier: Topic :: Software Development :: Code Generators
Requires-Dist: setuptools
